setup.py
vdgalcon-server.py
vdgalcon.py
vdgalcon.egg-info/PKG-INFO
vdgalcon.egg-info/SOURCES.txt
vdgalcon.egg-info/dependency_links.txt
vdgalcon.egg-info/requires.txt
vdgalcon.egg-info/top_level.txt