Metadata-Version: 1.1
Name: vdgalcon
Version: 1.11
Summary: Galactic Conquest in curses, on VisiData
Home-page: http://github.com/saulpw/vdgalcon
Author: Saul Pwanson
Author-email: vdgalcon@saul.pw
License: GPLv3
Download-URL: https://github.com/saulpw/vdgalcon/tarball/1.11
Keywords: console game textpunk visidata galactic conquest galcon
Platform: UNKNOWN
Classifier: Development Status :: 3 - Alpha
Classifier: Environment :: Console
Classifier: Environment :: Console :: Curses
Classifier: Intended Audience :: Developers
Classifier: Operating System :: OS Independent
Classifier: Programming Language :: Python :: 3
Classifier: Topic :: Office/Business :: Financial :: Spreadsheet
